{
    "Weapon": {
        "club": {
            "weapon_category": "simple",
            "weapon_range": "melee",
            "damage_dice": "1d4",
            "damage_bonus": 0,
            "damage_type": "bludgeoning",
            "range_normal": 5,
            "range_long": null,
            "cost": "1 sp",
            "weight": 2,
            "properties": [
                "light",
                "monk"
            ]
        },
        "dagger": {
            "weapon_category": "simple",
            "weapon_range": "melee",
            "damage_dice": "1d4",
            "damage_bonus": 0,
            "damage_type": "piercing",
            "range_normal": 5,
            "range_long": null,
            "cost": "2 gp",
            "weight": 1,
            "properties": [
                "finesse",
                "light",
                "thrown",
                "monk"
            ]
        },
        "greatclub": {
            "weapon_category": "simple",
            "weapon_range": "melee",
            "damage_dice": "1d8",
            "damage_bonus": 0,
            "damage_type": "bludgeoning",
            "range_normal": 5,
            "range_long": null,
            "cost": "2 sp",
            "weight": 10,
            "properties": [
                "two-handed"
            ]
        },
        "handaxe": {
            "weapon_category": "simple",
            "weapon_range": "melee",
            "damage_dice": "1d6",
            "damage_bonus": 0,
            "damage_type": "slashing",
            "range_normal": 5,
            "range_long": null,
            "cost": "5 gp",
            "weight": 2,
            "properties": [
                "light",
                "thrown",
                "monk"
            ]
        },
        "javelin": {
            "weapon_category": "simple",
            "weapon_range": "melee",
            "damage_dice": "1d6",
            "damage_bonus": 0,
            "damage_type": "piercing",
            "range_normal": 5,
            "range_long": null,
            "cost": "5 sp",
            "weight": 2,
            "properties": [
                "thrown",
                "monk"
            ]
        },
        "light hammer": {
            "weapon_category": "simple",
            "weapon_range": "melee",
            "damage_dice": "1d4",
            "damage_bonus": 0,
            "damage_type": "bludgeoning",
            "range_normal": 5,
            "range_long": null,
            "cost": "2 gp",
            "weight": 2,
            "properties": [
                "light",
                "thrown",
                "monk"
            ]
        },
        "mace": {
            "weapon_category": "simple",
            "weapon_range": "melee",
            "damage_dice": "1d6",
            "damage_bonus": 0,
            "damage_type": "bludgeoning",
            "range_normal": 5,
            "range_long": null,
            "cost": "5 gp",
            "weight": 4,
            "properties": [
                "monk"
            ]
        },
        "quarterstaff": {
            "weapon_category": "simple",
            "weapon_range": "melee",
            "damage_dice": "1d6",
            "damage_bonus": 0,
            "damage_type": "bludgeoning",
            "range_normal": 5,
            "range_long": null,
            "cost": "2 sp",
            "weight": 4,
            "properties": [
                "versatile",
                "monk"
            ]
        },
        "sickle": {
            "weapon_category": "simple",
            "weapon_range": "melee",
            "damage_dice": "1d4",
            "damage_bonus": 0,
            "damage_type": "slashing",
            "range_normal": 5,
            "range_long": null,
            "cost": "1 gp",
            "weight": 2,
            "properties": [
                "light",
                "monk"
            ]
        },
        "spear": {
            "weapon_category": "simple",
            "weapon_range": "melee",
            "damage_dice": "1d4",
            "damage_bonus": 0,
            "damage_type": "piercing",
            "range_normal": 5,
            "range_long": null,
            "cost": "1 gp",
            "weight": 3,
            "properties": [
                "thrown",
                "versatile",
                "monk"
            ]
        },
        "crossbow, light": {
            "weapon_category": "simple",
            "weapon_range": "ranged",
            "damage_dice": "1d8",
            "damage_bonus": 0,
            "damage_type": "piercing",
            "range_normal": 80,
            "range_long": 320,
            "cost": "25 gp",
            "weight": 5,
            "properties": [
                "ammunition",
                "loading",
                "two-handed"
            ]
        },
        "dart": {
            "weapon_category": "simple",
            "weapon_range": "ranged",
            "damage_dice": "1d4",
            "damage_bonus": 0,
            "damage_type": "piercing",
            "range_normal": 20,
            "range_long": 60,
            "cost": "5 cp",
            "weight": 0.25,
            "properties": [
                "finesse",
                "thrown"
            ]
        },
        "shortbow": {
            "weapon_category": "simple",
            "weapon_range": "ranged",
            "damage_dice": "1d6",
            "damage_bonus": 0,
            "damage_type": "piercing",
            "range_normal": 80,
            "range_long": 320,
            "cost": "25 gp",
            "weight": 2,
            "properties": [
                "ammunition",
                "two-handed"
            ]
        },
        "sling": {
            "weapon_category": "simple",
            "weapon_range": "ranged",
            "damage_dice": "1d4",
            "damage_bonus": 0,
            "damage_type": "bludgeoning",
            "range_normal": 30,
            "range_long": 120,
            "cost": "1 sp",
            "weight": 0,
            "properties": [
                "ammunition"
            ]
        },
        "battleaxe": {
            "weapon_category": "martial",
            "weapon_range": "melee",
            "damage_dice": "1d8",
            "damage_bonus": 0,
            "damage_type": "slashing",
            "range_normal": 5,
            "range_long": null,
            "cost": "10 gp",
            "weight": 4,
            "properties": [
                "versatile"
            ]
        },
        "flail": {
            "weapon_category": "martial",
            "weapon_range": "melee",
            "damage_dice": "1d8",
            "damage_bonus": 0,
            "damage_type": "bludgeoning",
            "range_normal": 5,
            "range_long": null,
            "cost": "10 gp",
            "weight": 2,
            "properties": []
        },
        "glaive": {
            "weapon_category": "martial",
            "weapon_range": "melee",
            "damage_dice": "1d10",
            "damage_bonus": 0,
            "damage_type": "slashing",
            "range_normal": 5,
            "range_long": null,
            "cost": "20 gp",
            "weight": 6,
            "properties": [
                "heavy",
                "reach",
                "two-handed"
            ]
        },
        "greataxe": {
            "weapon_category": "martial",
            "weapon_range": "melee",
            "damage_dice": "1d12",
            "damage_bonus": 0,
            "damage_type": "slashing",
            "range_normal": 5,
            "range_long": null,
            "cost": "30 gp",
            "weight": 7,
            "properties": [
                "heavy",
                "two-handed"
            ]
        },
        "greatsword": {
            "weapon_category": "martial",
            "weapon_range": "melee",
            "damage_dice": "2d6",
            "damage_bonus": 0,
            "damage_type": "slashing",
            "range_normal": 5,
            "range_long": null,
            "cost": "50 gp",
            "weight": 6,
            "properties": [
                "heavy",
                "two-handed"
            ]
        },
        "halberd": {
            "weapon_category": "martial",
            "weapon_range": "melee",
            "damage_dice": "1d10",
            "damage_bonus": 0,
            "damage_type": "slashing",
            "range_normal": 5,
            "range_long": null,
            "cost": "20 gp",
            "weight": 6,
            "properties": [
                "heavy",
                "reach",
                "two-handed"
            ]
        },
        "lance": {
            "weapon_category": "martial",
            "weapon_range": "melee",
            "damage_dice": "1d12",
            "damage_bonus": 0,
            "damage_type": "piercing",
            "range_normal": 5,
            "range_long": null,
            "cost": "10 gp",
            "weight": 6,
            "properties": [
                "reach",
                "special"
            ]
        },
        "longsword": {
            "weapon_category": "martial",
            "weapon_range": "melee",
            "damage_dice": "1d8",
            "damage_bonus": 0,
            "damage_type": "slashing",
            "range_normal": 5,
            "range_long": null,
            "cost": "15 gp",
            "weight": 3,
            "properties": [
                "versatile"
            ]
        },
        "maul": {
            "weapon_category": "martial",
            "weapon_range": "melee",
            "damage_dice": "2d6",
            "damage_bonus": 0,
            "damage_type": "bludgeoning",
            "range_normal": 5,
            "range_long": null,
            "cost": "10 gp",
            "weight": 10,
            "properties": [
                "heavy",
                "two-handed"
            ]
        },
        "morningstar": {
            "weapon_category": "martial",
            "weapon_range": "melee",
            "damage_dice": "1d8",
            "damage_bonus": 0,
            "damage_type": "piercing",
            "range_normal": 5,
            "range_long": null,
            "cost": "15 gp",
            "weight": 4,
            "properties": []
        },
        "pike": {
            "weapon_category": "martial",
            "weapon_range": "melee",
            "damage_dice": "1d10",
            "damage_bonus": 0,
            "damage_type": "piercing",
            "range_normal": 5,
            "range_long": null,
            "cost": "5 gp",
            "weight": 18,
            "properties": [
                "heavy",
                "reach",
                "two-handed"
            ]
        },
        "rapier": {
            "weapon_category": "martial",
            "weapon_range": "melee",
            "damage_dice": "1d8",
            "damage_bonus": 0,
            "damage_type": "piercing",
            "range_normal": 5,
            "range_long": null,
            "cost": "25 gp",
            "weight": 2,
            "properties": [
                "finesse"
            ]
        },
        "scimitar": {
            "weapon_category": "martial",
            "weapon_range": "melee",
            "damage_dice": "1d6",
            "damage_bonus": 0,
            "damage_type": "slashing",
            "range_normal": 5,
            "range_long": null,
            "cost": "25 gp",
            "weight": 3,
            "properties": [
                "finesse",
                "light"
            ]
        },
        "shortsword": {
            "weapon_category": "martial",
            "weapon_range": "melee",
            "damage_dice": "1d6",
            "damage_bonus": 0,
            "damage_type": "piercing",
            "range_normal": 5,
            "range_long": null,
            "cost": "10 gp",
            "weight": 2,
            "properties": [
                "finesse",
                "light",
                "monk"
            ]
        },
        "trident": {
            "weapon_category": "martial",
            "weapon_range": "melee",
            "damage_dice": "1d6",
            "damage_bonus": 0,
            "damage_type": "slashing",
            "range_normal": 5,
            "range_long": null,
            "cost": "5 gp",
            "weight": 4,
            "properties": [
                "thrown",
                "versatile"
            ]
        },
        "war pick": {
            "weapon_category": "martial",
            "weapon_range": "melee",
            "damage_dice": "1d8",
            "damage_bonus": 0,
            "damage_type": "piercing",
            "range_normal": 5,
            "range_long": null,
            "cost": "5 gp",
            "weight": 2,
            "properties": []
        },
        "warhammer": {
            "weapon_category": "martial",
            "weapon_range": "melee",
            "damage_dice": "1d8",
            "damage_bonus": 0,
            "damage_type": "bludgeoning",
            "range_normal": 5,
            "range_long": null,
            "cost": "15 gp",
            "weight": 2,
            "properties": [
                "versatile"
            ]
        },
        "whip": {
            "weapon_category": "martial",
            "weapon_range": "melee",
            "damage_dice": "1d4",
            "damage_bonus": 0,
            "damage_type": "slashing",
            "range_normal": 5,
            "range_long": null,
            "cost": "2 gp",
            "weight": 3,
            "properties": [
                "finesse",
                "reach"
            ]
        },
        "blowgun": {
            "weapon_category": "martial",
            "weapon_range": "ranged",
            "damage_dice": "1d1",
            "damage_bonus": 0,
            "damage_type": "piercing",
            "range_normal": 25,
            "range_long": 100,
            "cost": "10 gp",
            "weight": 1,
            "properties": [
                "ammunition",
                "loading"
            ]
        },
        "crossbow, hand": {
            "weapon_category": "martial",
            "weapon_range": "ranged",
            "damage_dice": "1d6",
            "damage_bonus": 0,
            "damage_type": "piercing",
            "range_normal": 30,
            "range_long": 120,
            "cost": "75 gp",
            "weight": 3,
            "properties": [
                "ammunition",
                "light",
                "loading"
            ]
        },
        "crossbow, heavy": {
            "weapon_category": "martial",
            "weapon_range": "ranged",
            "damage_dice": "1d10",
            "damage_bonus": 0,
            "damage_type": "piercing",
            "range_normal": 100,
            "range_long": 400,
            "cost": "50 gp",
            "weight": 18,
            "properties": [
                "ammunition",
                "light",
                "loading",
                "two-handed"
            ]
        },
        "longbow": {
            "weapon_category": "martial",
            "weapon_range": "ranged",
            "damage_dice": "1d8",
            "damage_bonus": 0,
            "damage_type": "piercing",
            "range_normal": 150,
            "range_long": 600,
            "cost": "50 gp",
            "weight": 2,
            "properties": [
                "ammunition",
                "heavy",
                "two-handed"
            ]
        },
        "net": {
            "weapon_category": "martial",
            "weapon_range": "ranged",
            "damage_dice": "1d0",
            "damage_bonus": 0,
            "damage_type": "slashing",
            "range_normal": 5,
            "range_long": 15,
            "cost": "1 gp",
            "weight": 3,
            "properties": [
                "thrown",
                "special"
            ]
        }
    },
    "Shield": {
        "shield": {
            "name": "Shield",
            "base": 2,
            "cost": "10 gp",
            "weight": 6
        }
    },
    "Armor": {
        "padded armor": {
            "category": "light",
            "base": 11,
            "dex_bonus": true,
            "max_bonus": null,
            "cost": "5 gp",
            "weight": 8
        },
        "leather armor": {
            "category": "light",
            "base": 11,
            "dex_bonus": true,
            "max_bonus": null,
            "cost": "10 gp",
            "weight": 10
        },
        "studded leather armor": {
            "category": "light",
            "base": 12,
            "dex_bonus": true,
            "max_bonus": null,
            "cost": "45 gp",
            "weight": 13
        },
        "hide armor": {
            "category": "medium",
            "base": 12,
            "dex_bonus": true,
            "max_bonus": 2,
            "cost": "10 gp",
            "weight": 12
        },
        "chain shirt armor": {
            "category": "medium",
            "base": 13,
            "dex_bonus": true,
            "max_bonus": 2,
            "cost": "50 gp",
            "weight": 20
        },
        "scale mail armor": {
            "category": "medium",
            "base": 14,
            "dex_bonus": true,
            "max_bonus": 2,
            "cost": "50 gp",
            "weight": 45
        },
        "breastplate armor": {
            "category": "medium",
            "base": 14,
            "dex_bonus": true,
            "max_bonus": 2,
            "cost": "400 gp",
            "weight": 20
        },
        "half plate armor": {
            "category": "medium",
            "base": 15,
            "dex_bonus": true,
            "max_bonus": 2,
            "cost": "750 gp",
            "weight": 40
        },
        "ring mail armor": {
            "category": "heavy",
            "base": 14,
            "dex_bonus": false,
            "max_bonus": null,
            "cost": "30 gp",
            "weight": 40
        },
        "chain mail armor": {
            "category": "heavy",
            "base": 16,
            "dex_bonus": false,
            "max_bonus": null,
            "cost": "75 gp",
            "weight": 55
        },
        "splint armor": {
            "category": "heavy",
            "base": 17,
            "dex_bonus": false,
            "max_bonus": null,
            "cost": "200 gp",
            "weight": 60
        },
        "plate armor": {
            "category": "heavy",
            "base": 18,
            "dex_bonus": false,
            "max_bonus": null,
            "cost": "1500 gp",
            "weight": 65
        }
    },
    "Item": {}
}